integral_deid/__init__.py
integral_deid/argmax_process.py
integral_deid/check_consistent_length.py
integral_deid/clean_regex.py
integral_deid/clinical_regex.py
integral_deid/clinical_spacy_tokenizer.py
integral_deid/conditional_random_field_sub.py
integral_deid/core_nlp_tokenizer.py
integral_deid/crf_argmax_process.py
integral_deid/crf_bert_model_for_token_classification.py
integral_deid/crf_process.py
integral_deid/crf_token_classifier_output.py
integral_deid/crf_utils.py
integral_deid/data_training_arguments.py
integral_deid/dataset.py
integral_deid/dataset_creator.py
integral_deid/dataset_tokenizer.py
integral_deid/date_regex.py
integral_deid/evaluation_arguments.py
integral_deid/label_mapper.py
integral_deid/logits_process.py
integral_deid/mismatch_error.py
integral_deid/model_arguments.py
integral_deid/model_picker.py
integral_deid/ner_dataset.py
integral_deid/ner_labels.py
integral_deid/ner_predict_token_labels.py
integral_deid/ner_token_labels.py
integral_deid/note_level_aggregator.py
integral_deid/note_sentencizer.py
integral_deid/post_process_picker.py
integral_deid/preprocessing_loader.py
integral_deid/sentence_dataset.py
integral_deid/sequence_tagging.py
integral_deid/spacy_sentencizer.py
integral_deid/spacy_tokenizer.py
integral_deid/text_deid.py
integral_deid/text_deid_utils.py
integral_deid/threshold_process_max.py
integral_deid/threshold_process_sum.py
integral_deid-2024.9.11.dist-info/METADATA
integral_deid-2024.9.11.dist-info/WHEEL
integral_deid-2024.9.11.dist-info/RECORD
