Metadata-Version: 2.1
Name: integral_deid
Version: 2024.9.11
Summary: PHI taggging and redaction
Author: Kevin DeSimone
Author-email: kevin@useintegral.com
Requires-Python: >=3.10,<4.0
Classifier: Programming Language :: Python :: 3
Classifier: Programming Language :: Python :: 3.10
Classifier: Programming Language :: Python :: 3.11
Classifier: Programming Language :: Python :: 3.12
Requires-Dist: accelerate (==0.28.0)
Requires-Dist: allennlp-light (==1.0.0)
Requires-Dist: databricks-sdk (==0.23.0)
Requires-Dist: datasets (==2.18.0)
Requires-Dist: markupsafe (==2.0.1)
Requires-Dist: pandas (==2.2.1)
Requires-Dist: pycorenlp (==0.3.0)
Requires-Dist: seqeval (==1.2.2)
Requires-Dist: spacy (==3.7.4)
Requires-Dist: tensorboard (==2.16.2)
Requires-Dist: torch (==2.2.1)
Requires-Dist: transformers (==4.39.1)
